dask_igzip/__init__.py
dask_igzip/__version__.py
dask_igzip/text.py
dask_igzip-0.2.0.dist-info/DESCRIPTION.rst
dask_igzip-0.2.0.dist-info/METADATA
dask_igzip-0.2.0.dist-info/RECORD
dask_igzip-0.2.0.dist-info/WHEEL
dask_igzip-0.2.0.dist-info/metadata.json
dask_igzip-0.2.0.dist-info/top_level.txt
