Metadata-Version: 2.0
Name: dask-igzip
Version: 0.2.0
Summary: dask chunked read_text on gzip file
Home-page: https://github.com/jurismarches/dask-igzip
Author: Jurismarches
Author-email: contact@jurismarches.com
License: UNKNOWN
Platform: UNKNOWN
Classifier: Development Status :: 3 - Alpha
Classifier: License :: OSI Approved :: GNU Lesser General Public License v3 or later (LGPLv3+)
Classifier: Topic :: Scientific/Engineering :: Information Analysis
Classifier: Intended Audience :: Developers
Classifier: Intended Audience :: Science/Research
Classifier: Programming Language :: Python
Classifier: Programming Language :: Python :: 3.5
Classifier: Programming Language :: Python :: 3.6
Provides-Extra: tests
Requires-Dist: dask[bag] (>=0.17.5)
Requires-Dist: indexed-gzip (>=0.8.5)
Provides-Extra: tests
Requires-Dist: distributed (>=1.22); extra == 'tests'
Requires-Dist: flake8 (>=3.5.0); extra == 'tests'
Requires-Dist: pytest-cov (>=2.5.1); extra == 'tests'
Requires-Dist: pytest (>=3.4.2); extra == 'tests'
